phinka/CHANGE-LOG.md
phinka/LICENSE.txt
phinka/README.md
phinka/__init__.py
phinka/__main__.py
phinka/blwz.py
phinka/decorate.py
phinka/dx.py
phinka/types.py
phinka-1.0.4.dist-info/METADATA
phinka-1.0.4.dist-info/WHEEL
phinka-1.0.4.dist-info/RECORD
